sld/__init__.py
sld/slidebook.py
sld/yaml.py
slidebook_python-0.0.3.dist-info/LICENSE
slidebook_python-0.0.3.dist-info/METADATA
slidebook_python-0.0.3.dist-info/WHEEL
slidebook_python-0.0.3.dist-info/top_level.txt
slidebook_python-0.0.3.dist-info/RECORD
