Metadata-Version: 2.1
Name: slidebook-python
Version: 0.0.3
Summary: Open slidebook .sldy files in Python
Home-page: https://github.com/instituteofcancerresearch/slidebook-python
Author: Adam Tyson
Author-email: code@adamltyson.com
License: MIT
Project-URL: Source, https://github.com/instituteofcancerresearch/slidebook-python
Project-URL: Tracker, https://github.com/instituteofcancerresearch/slidebook-python/issues
Platform: UNKNOWN
Classifier: Development Status :: 3 - Alpha
Classifier: Intended Audience :: Developers
Classifier: Programming Language :: Python
Classifier: Programming Language :: Python :: 3 :: Only
Classifier: Programming Language :: Python :: 3.9
Classifier: Programming Language :: Python :: 3.10
Requires-Python: >=3.9
License-File: LICENSE
Requires-Dist: numpy
Provides-Extra: dev
Requires-Dist: black ; extra == 'dev'
Requires-Dist: pytest ; extra == 'dev'
Requires-Dist: pytest-cov ; extra == 'dev'
Requires-Dist: bump2version ; extra == 'dev'
Requires-Dist: pre-commit ; extra == 'dev'
Requires-Dist: flake8 ; extra == 'dev'
Requires-Dist: coverage ; extra == 'dev'
Requires-Dist: mypy ; extra == 'dev'
Requires-Dist: types-PyYAML ; extra == 'dev'
